[

{
  "id": "htu_700",
  "kind": "subject",
  "sid": "htu_700_add"
},
{
  "id": "htu_title_710",
  "kind": "title",
  "sid": "htu_711_pa3",
  "align": "center",
  "fullWidth": true
},
{
  "id": "htu_card_710",
  "kind": "card",
  "src": "/images/howtouse/htu_710_distance.jpg",
  "altSid": "htu_img_710_alt",
  "titleSid": "",
  "bodySids": [
    "htu_712_180",
    "htu_713_dis"
  ],
  "ratio": "2 / 1",
  "fit": "contain",
  "fullWidth": true
},
{
  "id": "htu_remark_721",
  "kind": "remark",
  "titleSid": "",
  "bodySids": [
    { "sid": "htu_722_rgf" },
    { "sid": "htu_723_det" }
  ],
  "align": "center",
  "fullWidth": true
},
  {
    "id": "htu_100",
    "kind": "subject",
    "sid": "htu_100_und"
  },

  {
    "id": "htu_title_110",
    "kind": "title",
    "sid": "htu_111_hpl",
    "align": "center",
    "fullWidth": true
  },
  {
    "id": "htu_card_110a",
    "kind": "card",
    "src": "/images/howtouse/htu_110.jpg",
    "altSid": "htu_img_110_alt",
    "titleSid": "",
    "bodySids": [
      { "sid": "htu_112_hom", "align": "center" }
    ],
    "fit": "contain",
    "fullWidth": true
  },

  {
    "id": "htu_title_120",
    "kind": "title",
    "sid": "htu_121_mai",
    "align": "center",
    "fullWidth": true
  },
  {
    "id": "htu_card_120a",
    "kind": "card",
    "src": "/images/howtouse/htu_120.jpg",
    "altSid": "htu_img_120_alt",
    "titleSid": "",
    "bodySids": [
      "htu_122_top",
      "htu_123_hom",
      "htu_124_sub",
      "htu_125_str",
      "htu_132_sid",
      "htu_133_sho"
    ],
    "fit": "contain",
    "fullWidth": true
  },

  {
    "id": "htu_title_150",
    "kind": "title",
    "sid": "htu_151_scr",
    "align": "center",
    "fullWidth": true
  },
  {
    "id": "htu_card_150a",
    "kind": "card",
    "src": "/images/howtouse/htu_150.jpg",
    "altSid": "htu_img_150_alt",
    "titleSid": "",
    "bodySids": [
      { "sid": "htu_152_str", "align": "center" }
    ],
    "fit": "contain",
    "fullWidth": true
  },
  {
    "id": "htu_remark_150",
    "kind": "remark",
    "sid": "htu_154_mix",
    "align": "center",
    "fullWidth": true
  },

  {
    "id": "htu_title_160",
    "kind": "title",
    "sid": "htu_161_set",
    "align": "center",
    "fullWidth": true
  },
  {
    "id": "htu_card_160a",
    "kind": "card",
    "src": "/images/howtouse/htu_160.jpg",
    "altSid": "htu_img_160_alt",
    "titleSid": "",
    "bodySids": [
      { "sid": "htu_162_new", "align": "center" },
      {
        "parts":[
          {"sid":"htu_163_tab"},
          {"icon":"/images/icons/a7_config.png"}
        ]
      }
    ],
    "fit": "contain",
    "fullWidth": true
  },
  {
    "id": "htu_spacer_1",
    "kind": "spacer",
    "size": "lg"
  },

  {
    "id": "htu_200",
    "kind": "subject",
    "sid": "htu_200_hpm"
  },

  {
    "id": "htu_title_210",
    "kind": "title",
    "sid": "htu_211_per",
    "align": "center",
    "fullWidth": true
  },
  {
    "id": "htu_card_210a",
    "kind": "card",
    "src": "/images/howtouse/htu_210.jpg",
    "altSid": "htu_img_210_alt",
    "titleSid": "",
    "bodySids": [
      {
        "parts":[
          {"sid":"htu_212_aft"},
          {"icon":"/images/icons/a2_ar.png"},
          {"icon":"/images/icons/a3_blue.png"}
        ]
      },
      "htu_213_you"
    ],
    "fit": "contain",
    "fullWidth": true
  },
  {
    "id": "htu_title_220",
    "kind": "title",
    "sid": "htu_221_ind",
    "align": "center",
    "fullWidth": true
  },
  {
    "id": "htu_card_220a",
    "kind": "card",
    "src": "/images/howtouse/htu_220.jpg",
    "altSid": "htu_img_220_alt",
    "titleSid": "",
    "bodySids": [
      "htu_222_use"
    ],
     "fit": "contain",
    "fullWidth": true
  },
  {
    "id": "htu_title_230",
    "kind": "title",
    "sid": "htu_231_out",
    "align": "center",
    "fullWidth": true
  },
  {
    "id": "htu_card_230",
    "kind": "card",
    "src": "/images/howtouse/htu_230.jpg",
    "altSid": "htu_img_230_alt",
    "titleSid": "",
    "bodySids": [
      { "sid": "htu_232_wor", "align": "center" }
    ],
    "ratio": "2 / 1",
    "fit": "contain",
    "fullWidth": true
  },

  {
    "id": "htu_title_240",
    "kind": "title",
    "sid": "htu_241_rea",
    "align": "center",
    "fullWidth": true
  },
  {
    "id": "htu_card_240a",
    "kind": "card",
    "src": "/images/howtouse/htu_240.jpg",
    "altSid": "htu_img_240_alt",
    "titleSid": "",
    "bodySids": [
      "htu_242_bal",
      "htu_243_ano",
      "htu_244_bas",
      "htu_245_nex"
    ],
    "fit": "contain",
    "fullWidth": true
  },

  {
    "id": "htu_spacer_2",
    "kind": "spacer",
    "size": "sm"
  },

  {
    "id": "htu_300_how",
    "kind": "subject",
    "sid": "htu_300_how"
  },

  {
    "id": "htu_title_310",
    "kind": "title",
    "sid": "htu_311_arm",
    "align": "center",
    "fullWidth": true
  },
  {
    "id": "htu_card_310a",
    "kind": "card",
    "src": "/images/howtouse/htu_310.jpg",
    "altSid": "htu_img_310_alt",
    "titleSid": "",
    "bodySids": [],
    "fit": "contain",
    "fullWidth": true
  },
  {
    "id": "htu_title_320",
    "kind": "title",
    "sid": "htu_321_arm",
    "align": "center",
    "fullWidth": true
  },
  {
    "id": "htu_card_320",
    "kind": "card",
    "src": "/images/howtouse/htu_320.jpg",
    "altSid": "htu_img_320_alt",
    "titleSid": "",
    "bodySids": [],
    "fit": "contain",
    "fullWidth": true
  },

  {
    "id": "htu_card_330",
    "kind": "card",
    "src": "/images/howtouse/htu_330.jpg",
    "altSid": "htu_img_330_alt",
    "titleSid": "",
    "bodySids": [
      { "sid": "htu_332_tab", "align": "center" },
      { "sid": "htu_342_tvs", "align": "center" }
    ],
    "fit": "contain",
    "fullWidth": true
  },

  {
    "id": "htu_400",
    "kind": "subject",
    "sid": "htu_400_imp"
  },

  {
    "id": "htu_title_410",
    "kind": "title",
    "sid": "htu_411_bef",
    "align": "center",
    "fullWidth": true
  },
  {
    "id": "htu_card_410a",
    "kind": "card",
    "src": "/images/howtouse/htu_410_before.jpg",
    "altSid": "htu_img_410_alt",
    "titleSid": "",
    "bodySids": [
      "htu_412_act"
    ],
    "fit": "contain",
    "fullWidth": true
  },

  {
    "id": "htu_title_420",
    "kind": "title",
    "sid": "htu_421_aft",
    "align": "center",
    "fullWidth": true
  },
  {
    "id": "htu_card_420a",
    "kind": "card",
    "src": "/images/howtouse/htu_420_after.jpg",
    "altSid": "htu_img_420_alt",
    "titleSid": "",
    "bodySids": [
      "htu_422_act",
      "htu_423_dra",
      "htu_424_thn"
    ],
    "fit": "contain",
    "fullWidth": true
  },
  {
    "id": "htu_remark_425",
    "kind": "remark",
    "titleSid": "",
    "bodySids": [
      {
        "parts":[
          {"sid":"htu_425_r1_dbl"},
          {"icon":"/images/icons/d2r_double.png"},
          {"sid":"htu_426_r2_oth"},
          {"icon":"/images/icons/d1r_single.png"},
          {"icon":"/images/icons/d2_double.png"}
        ]
      }
    ],
    "align": "center",
    "fullWidth": true
  },
  {
    "id": "htu_500",
    "kind": "subject",
    "sid": "htu_500_exa"
  },

  {
    "id": "htu_title_510",
    "kind": "title",
    "sid": "htu_511_hor",
    "align": "center",
    "fullWidth": true
  },
  {
    "id": "htu_card_510a",
    "kind": "card",
    "src": "/images/howtouse/htu_510d_horizontal.jpg",
    "altSid": "htu_img_510_alt",
    "titleSid": "",
    "bodySids": [
      "htu_512_1975",
      "htu_513_1987"
    ],
    "fit": "contain",
    "fullWidth": true
  },
  {
    "id": "htu_title_520",
    "kind": "title",
    "sid": "htu_521_ver",
    "align": "center",
    "fullWidth": true
  },
  {
    "id": "htu_card_520a",
    "kind": "card",
    "src": "/images/howtouse/htu_520d_vertical.jpg",
    "altSid": "htu_img_520_alt",
    "titleSid": "",
    "bodySids": [
      "htu_522_2150",
      "htu_523_2141",
      "htu_524_2137"
    ],
    "fit": "contain",
    "fullWidth": true
  },
{
  "id": "htu_600",
  "kind": "subject",
  "sid": "htu_600_aut"
},

{
  "id": "htu_title_610",
  "kind": "title",
  "sid": "htu_611_pla",
  "align": "center",
  "fullWidth": true
},
{
  "id": "htu_card_610",
  "kind": "card",
  "src": "/images/howtouse/htu_610_autoplace.jpg",
  "altSid": "htu_img_610_alt",
  "titleSid": "",
  "bodySids": [
    "htu_612_non",
    "htu_613_usi"
  ],
  "fit": "contain",
  "fullWidth": true
},

{
  "id": "htu_title_620",
  "kind": "title",
  "sid": "htu_621_non",
  "align": "center",
  "fullWidth": true
},
{
  "id": "htu_card_620",
  "kind": "card",
  "src": "/images/howtouse/htu_620_autodraw.jpg",
  "altSid": "htu_img_620_alt",
  "titleSid": "",
  "bodySids": [
      {
        "parts":[
          {"sid":"htu_622_whn"},
          {"icon":"/images/icons/a5_red.png"},
          {"icon":"/images/icons/a6_load.png"},
          {"icon":"/images/icons/d1r_single.png"}
        ]
      },
      "htu_623_dim",
      {
        "parts":[
          {"sid":"htu_624_siz"},
          {"icon":"/images/icons/a7_config.png"}
        ]
      }
  ],
  "ratio": "2 / 1",
  "fit": "contain",
  "fullWidth": true
},

{
  "id": "htu_remark_631",
  "kind": "remark",
  "titleSid": "htu_631_con",
  "bodySids": [
    { "sid": "htu_632_wor"},
    { "sid": "htu_633_ava"},
    { "sid":"htu_634_req"}

  ],
  "align": "center",
  "fullWidth": true
},

  {
    "id": "htu_800",
    "kind": "subject",
    "sid": "htu_800_sub"
  },
  {
    "id": "htu_810",
    "kind": "remark",
    "titleSid": "htu_810_rtitle",
    "bodySids": [
      "htu_811_r1_this"
    ],
    "fullWidth": true
  },
  {
    "id": "htu_812",
    "kind": "card",
    "titleSid": "htu_812_ctitle",
    "bodySids": [
      "htu_812_b1_prep",
      "htu_813_b2_iden",
      "htu_814_b3_set"
    ],
    "fullWidth": true
  },

  {
    "id": "htu_card_820",
    "kind": "card",
    "src": "/images/howtouse/htu_820_triangle.jpg",
    "altSid": "htu_img_820_alt",
    "titleSid": "htu_820_title",
    "bodySids": [
      "htu_821_b1_photo",
      {
        "parts":[
          {"sid":"htu_822_b2_red"},
          {"icon":"/images/icons/a5_red.png"},
          {"icon":"/images/icons/a6_load.png"}
        ]
      },
      {
        "parts":[
          {"sid":"htu_823_b3_three"},
          {"icon":"/images/icons/d3r_triangle.png"}
        ]
      },
      {
        "parts":[
          {"sid":"htu_824_b4_move"},
          {"icon":"/images/icons/b3r_move.png"}
        ]
      },
      "htu_825_b5_align"
    ],
    "align": "left",
    "fullWidth": true
  },

  {
    "id": "htu_card_826",
    "kind": "card",
    "src": "/images/howtouse/htu_826_line.jpg",
    "altSid": "htu_img_826_alt",
    "titleSid": "",
    "bodySids": [
      "htu_826_b6_enter",
      {
        "parts":[
          {"sid":"htu_827_b7_blue"},
          {"icon":"/images/icons/a3_blue.png"}
        ]
      },
      {
        "parts":[
          {"sid":"htu_828_b8_come"},
          {"icon":"/images/icons/a5_red.png"},
          {"icon":"/images/icons/d4_convert.png"}
        ]
      }
    ],
    "align": "left",
    "fullWidth": true
  },
  {
    "id": "htu_831",
    "kind": "remark",
    "titleSid": "",
    "bodySids": [
      "htu_831_rb1_prac"
    ],
    "align": "center",
    "fullWidth": true
  },

  {
    "id": "htu_840",
    "kind": "subject",
    "sid": "htu_840_sub"
  },
  {
    "id": "htu_card_841",
    "kind": "card",
    "src": "/images/howtouse/htu_841.jpg",
    "altSid": "htu_img_841_alt",
    "titleSid": "htu_841_ctitle",
    "bodySids": [
      "htu_841_b1",
      {
        "parts":[
          {"sid":"htu_842_b2"},
          {"icon":"/images/icons/a5_red.png"},
          {"icon":"/images/icons/d1r_single.png"}
        ]
      },
      {
        "parts":[
          {"sid":"htu_843_b3"},
          {"icon":"/images/icons/b3r_move.png"}
        ]
      },
      {
        "parts":[
          {"sid":"htu_844_b4"},
          {"icon":"/images/icons/a3_blue.png"},
          {"icon":"/images/icons/b3r_move.png"}
        ]
      }
    ],
    "align": "left",
    "fullWidth": true
  },
  {
    "id": "htu_845",
    "kind": "remark",
    "titleSid": "",
    "bodySids": [
      "htu_845_r1"
    ],
    "align": "center",
    "fullWidth": true
  },

  {
    "id": "htu_card_851",
    "kind": "card",
    "src": "/images/howtouse/htu_851.jpg",
    "altSid": "htu_img_851_alt",
    "titleSid": "htu_851_ctitle",
    "bodySids": [
      "htu_851_b1",
      "htu_852_b2",
      {
        "parts":[
          {"sid":"htu_853_b3"},
          {"icon":"/images/icons/a5_red.png"}
        ]
      },
      {
        "parts":[
          {"sid":"htu_854_b4"},
          {"icon":"/images/icons/b3r_move.png"}
        ]
      },
      "htu_855_b5",
      "htu_856_b6",
      {
        "parts":[
          {"sid":"htu_857_b7"},
          {"icon":"/images/icons/a3_blue.png"},
          {"icon":"/images/icons/b1_straight.png"},
          {"icon":"/images/icons/b1b_curve.png"}
        ]
      }
    ],
    "align": "left",
    "fullWidth": true
  },
  {
    "id": "htu_860",
    "kind": "remark",
    "titleSid": "htu_860_rt",
    "bodySids": [
      "htu_861_r1",
      "htu_862_r2",
      "htu_863_r3"
    ],
    "fullWidth": true
  },

  {
    "id": "htu_900",
    "kind": "subject",
    "sid": "htu_900_sub"
  },
  {
    "id": "htu_title_910",
    "kind": "title",
    "sid": "htu_910_title",
    "align": "center",
    "fullWidth": true
  },
  {
    "id": "htu_911",
    "kind": "card",
    "src": "/images/howtouse/htu_911.jpg",
    "altSid": "htu_img_911_alt",
    "titleSid": "htu_911_ctitle",
    "bodySids": [
       "htu_912_b1",
       "htu_913_b2",
       "htu_914_b3",
       "htu_915_b4",
       "htu_916_b5",
       "htu_917_b6",
       "htu_918_b7"
    ],
    "fullWidth": true
  }
]
